soa4onnx/__init__.py
soa4onnx/__main__.py
soa4onnx/onnx_model_output_adder.py
soa4onnx-1.0.4.dist-info/LICENSE
soa4onnx-1.0.4.dist-info/METADATA
soa4onnx-1.0.4.dist-info/WHEEL
soa4onnx-1.0.4.dist-info/entry_points.txt
soa4onnx-1.0.4.dist-info/top_level.txt
soa4onnx-1.0.4.dist-info/RECORD
