Metadata-Version: 2.1
Name: soa4onnx
Version: 1.0.4
Summary: Simple model output OP additional tools.
Home-page: https://github.com/PINTO0309/soa4onnx
Author: Katsuya Hyodo
Author-email: rmsdh122@yahoo.co.jp
License: MIT License
Platform: linux
Platform: unix
Requires-Python: >=3.6
License-File: LICENSE
